{
    "commit_hash": "317c68048c0664d8a1bed23a8580b8f136d76a38", 
    "date": 1503400962000, 
    "ended_at": {
        "api.supers.time_createadd": 1504887067000, 
        "api.supers.time_createadd_to_dataset": 1504887071000, 
        "api.supers.time_installr": 1504887082000, 
        "api.supers.time_ls": 1504887088000, 
        "api.supers.time_remove": 1504887100000, 
        "api.testds.time_create_test_dataset1": 1504887102000, 
        "api.testds.time_create_test_dataset2x2": 1504887110000, 
        "core.runner.time_echo": 1504887115000, 
        "core.runner.time_echo_gitrunner": 1504887121000, 
        "core.startup.time_help_np": 1504887123000, 
        "core.startup.time_import": 1504887126000, 
        "core.startup.time_import_api": 1504887128000
    }, 
    "env_name": "virtualenv-py2.7", 
    "params": {
        "arch": "x86_64", 
        "cpu": "Intel(R) Xeon(R) CPU E5-1607 v2 @ 3.00GHz", 
        "machine": "drogon-neurodebian1.1", 
        "os": "Linux 4.6.0-rc1+", 
        "python": "2.7", 
        "ram": "65948008"
    }, 
    "profiles": {}, 
    "python": "2.7", 
    "requirements": {}, 
    "results": {
        "api.supers.time_createadd": 1.1211531162261963, 
        "api.supers.time_createadd_to_dataset": 1.158588171005249, 
        "api.supers.time_installr": 3.5307259559631348, 
        "api.supers.time_ls": 0.134027099609375, 
        "api.supers.time_remove": 3.712898015975952, 
        "api.testds.time_create_test_dataset1": 0.3955209255218506, 
        "api.testds.time_create_test_dataset2x2": 2.561131000518799, 
        "core.runner.time_echo": 0.001574146032333374, 
        "core.runner.time_echo_gitrunner": 0.001824265956878662, 
        "core.startup.time_help_np": 0.44273900985717773, 
        "core.startup.time_import": 0.08973889350891114, 
        "core.startup.time_import_api": 0.3720099925994873
    }, 
    "started_at": {
        "api.supers.time_createadd": 1504887063000, 
        "api.supers.time_createadd_to_dataset": 1504887067000, 
        "api.supers.time_installr": 1504887071000, 
        "api.supers.time_ls": 1504887082000, 
        "api.supers.time_remove": 1504887088000, 
        "api.testds.time_create_test_dataset1": 1504887100000, 
        "api.testds.time_create_test_dataset2x2": 1504887102000, 
        "core.runner.time_echo": 1504887110000, 
        "core.runner.time_echo_gitrunner": 1504887115000, 
        "core.startup.time_help_np": 1504887121000, 
        "core.startup.time_import": 1504887123000, 
        "core.startup.time_import_api": 1504887126000
    }, 
    "version": 1
}