{
    "commit_hash": "3441a5b0401fab1b6784ea34574961d45015bc44", 
    "date": 1487604646000, 
    "ended_at": {
        "api.supers.time_createadd": 1504896270000, 
        "api.supers.time_createadd_to_dataset": 1504896274000, 
        "api.supers.time_installr": 1504896284000, 
        "api.supers.time_ls": 1504896284000, 
        "api.supers.time_ls_recursive": 1519428771000, 
        "api.supers.time_ls_recursive_long_all": 1519428772000, 
        "api.supers.time_remove": 1504896296000, 
        "api.testds.time_create_test_dataset1": 1504896297000, 
        "api.testds.time_create_test_dataset2x2": 1504896305000, 
        "core.runner.time_echo": 1504896309000, 
        "core.runner.time_echo_gitrunner": 1504896315000, 
        "core.startup.time_help_np": 1504896317000, 
        "core.startup.time_import": 1504896320000, 
        "core.startup.time_import_api": 1504896321000
    }, 
    "env_name": "virtualenv-py3.4", 
    "params": {
        "arch": "x86_64", 
        "cpu": "Intel(R) Xeon(R) CPU E5-1607 v2 @ 3.00GHz", 
        "machine": "drogon-neurodebian1.1", 
        "os": "Linux 4.6.0-rc1+", 
        "python": "3.4", 
        "ram": "65948008"
    }, 
    "profiles": {}, 
    "python": "3.4", 
    "requirements": {}, 
    "results": {
        "api.supers.time_createadd": 1.1510780239477754, 
        "api.supers.time_createadd_to_dataset": 1.3157162079587579, 
        "api.supers.time_installr": 2.823971960693598, 
        "api.supers.time_ls": null, 
        "api.supers.time_ls_recursive": null, 
        "api.supers.time_ls_recursive_long_all": null, 
        "api.supers.time_remove": 3.6787178264930844, 
        "api.testds.time_create_test_dataset1": 0.2766165900975466, 
        "api.testds.time_create_test_dataset2x2": 2.516450498253107, 
        "core.runner.time_echo": 0.001315426668152213, 
        "core.runner.time_echo_gitrunner": 0.0017776467129588128, 
        "core.startup.time_help_np": 0.4721232298761606, 
        "core.startup.time_import": 0.08633309155702591, 
        "core.startup.time_import_api": 0.23026645742356777
    }, 
    "started_at": {
        "api.supers.time_createadd": 1504896266000, 
        "api.supers.time_createadd_to_dataset": 1504896270000, 
        "api.supers.time_installr": 1504896274000, 
        "api.supers.time_ls": 1504896284000, 
        "api.supers.time_ls_recursive": 1519428770000, 
        "api.supers.time_ls_recursive_long_all": 1519428771000, 
        "api.supers.time_remove": 1504896284000, 
        "api.testds.time_create_test_dataset1": 1504896296000, 
        "api.testds.time_create_test_dataset2x2": 1504896297000, 
        "core.runner.time_echo": 1504896305000, 
        "core.runner.time_echo_gitrunner": 1504896309000, 
        "core.startup.time_help_np": 1504896315000, 
        "core.startup.time_import": 1504896317000, 
        "core.startup.time_import_api": 1504896320000
    }, 
    "version": 1
}