{
    "commit_hash": "363807c087a137c35a72b443b0be4809fd1d49e7", 
    "date": 1489648088000, 
    "ended_at": {
        "benchmarks.CreateTestDatasetSuite.time_create_test_dataset1": 1494536027000, 
        "benchmarks.CreateTestDatasetSuite.time_create_test_dataset2x2": 1494536034000, 
        "benchmarks.RunnerSuite.time_echo": 1494536039000, 
        "benchmarks.RunnerSuite.time_echo_gitrunner": 1494536044000, 
        "benchmarks.StartupSuite.time_help_np": 1494536045000, 
        "benchmarks.StartupSuite.time_import": 1494536048000, 
        "benchmarks.StartupSuite.time_import_api": 1494536054000, 
        "benchmarks.SuperdatasetsOperationsSuite.time_createadd": 1494536063000, 
        "benchmarks.SuperdatasetsOperationsSuite.time_createadd_to_dataset": 1494536067000, 
        "benchmarks.SuperdatasetsOperationsSuite.time_installr": 1494536075000, 
        "benchmarks.SuperdatasetsOperationsSuite.time_ls": 1494536079000, 
        "benchmarks.SuperdatasetsOperationsSuite.time_remove": 1494536089000
    }, 
    "env_name": "virtualenv-py2.7", 
    "params": {
        "arch": "x86_64", 
        "cpu": "Intel(R) Xeon(R) CPU E5-1607 v2 @ 3.00GHz", 
        "machine": "drogon-neurodebian1.1", 
        "os": "Linux 4.6.0-rc1+", 
        "python": "2.7", 
        "ram": "65948008"
    }, 
    "profiles": {}, 
    "python": "2.7", 
    "requirements": {}, 
    "results": {
        "benchmarks.CreateTestDatasetSuite.time_create_test_dataset1": 0.28159093856811523, 
        "benchmarks.CreateTestDatasetSuite.time_create_test_dataset2x2": 2.288909912109375, 
        "benchmarks.RunnerSuite.time_echo": 0.0013556540012359618, 
        "benchmarks.RunnerSuite.time_echo_gitrunner": 0.0015934839248657226, 
        "benchmarks.StartupSuite.time_help_np": 0.4327099323272705, 
        "benchmarks.StartupSuite.time_import": 0.06351361274719239, 
        "benchmarks.StartupSuite.time_import_api": 0.17670459747314454, 
        "benchmarks.SuperdatasetsOperationsSuite.time_createadd": 1.0212459564208984, 
        "benchmarks.SuperdatasetsOperationsSuite.time_createadd_to_dataset": 1.1825039386749268, 
        "benchmarks.SuperdatasetsOperationsSuite.time_installr": 2.5177111625671387, 
        "benchmarks.SuperdatasetsOperationsSuite.time_ls": 0.09315431118011475, 
        "benchmarks.SuperdatasetsOperationsSuite.time_remove": 3.0853278636932373
    }, 
    "started_at": {
        "benchmarks.CreateTestDatasetSuite.time_create_test_dataset1": 1494536026000, 
        "benchmarks.CreateTestDatasetSuite.time_create_test_dataset2x2": 1494536027000, 
        "benchmarks.RunnerSuite.time_echo": 1494536034000, 
        "benchmarks.RunnerSuite.time_echo_gitrunner": 1494536039000, 
        "benchmarks.StartupSuite.time_help_np": 1494536044000, 
        "benchmarks.StartupSuite.time_import": 1494536045000, 
        "benchmarks.StartupSuite.time_import_api": 1494536048000, 
        "benchmarks.SuperdatasetsOperationsSuite.time_createadd": 1494536059000, 
        "benchmarks.SuperdatasetsOperationsSuite.time_createadd_to_dataset": 1494536063000, 
        "benchmarks.SuperdatasetsOperationsSuite.time_installr": 1494536067000, 
        "benchmarks.SuperdatasetsOperationsSuite.time_ls": 1494536075000, 
        "benchmarks.SuperdatasetsOperationsSuite.time_remove": 1494536079000
    }, 
    "version": 1
}