{
    "commit_hash": "4c9253b9c7c6aa82520c054ba427aa116ec4062e", 
    "date": 1523074108000, 
    "ended_at": {
        "api.supers.time_createadd": 1523472108000, 
        "api.supers.time_createadd_to_dataset": 1523472112000, 
        "api.supers.time_installr": 1523472120000, 
        "api.supers.time_ls": 1523472124000, 
        "api.supers.time_ls_recursive": 1523472128000, 
        "api.supers.time_ls_recursive_long_all": 1523472133000, 
        "api.supers.time_remove": 1523472137000, 
        "api.testds.time_create_test_dataset1": 1523472138000, 
        "api.testds.time_create_test_dataset2x2": 1523472144000, 
        "core.runner.time_echo": 1523472149000, 
        "core.runner.time_echo_gitrunner": 1523472155000, 
        "core.startup.time_help_np": 1523472157000, 
        "core.startup.time_import": 1523472160000, 
        "core.startup.time_import_api": 1523472162000
    }, 
    "env_name": "virtualenv-py2.7", 
    "params": {
        "arch": "x86_64", 
        "cpu": "Intel(R) Xeon(R) CPU E5-1607 v2 @ 3.00GHz", 
        "machine": "drogon-neurodebian1.1", 
        "os": "Linux 4.6.0-rc1+", 
        "python": "2.7", 
        "ram": "65948008"
    }, 
    "profiles": {}, 
    "python": "2.7", 
    "requirements": {}, 
    "results": {
        "api.supers.time_createadd": 0.773190975189209, 
        "api.supers.time_createadd_to_dataset": 0.763742208480835, 
        "api.supers.time_installr": 2.496777057647705, 
        "api.supers.time_ls": 0.11452109813690185, 
        "api.supers.time_ls_recursive": 0.9726369380950928, 
        "api.supers.time_ls_recursive_long_all": 1.1770150661468506, 
        "api.supers.time_remove": 1.22135591506958, 
        "api.testds.time_create_test_dataset1": 0.23275303840637207, 
        "api.testds.time_create_test_dataset2x2": 1.5338881015777588, 
        "core.runner.time_echo": 0.0015375938415527345, 
        "core.runner.time_echo_gitrunner": 0.0017723350524902345, 
        "core.startup.time_help_np": 0.5132031440734863, 
        "core.startup.time_import": 0.07423779964447022, 
        "core.startup.time_import_api": 0.44738101959228516
    }, 
    "started_at": {
        "api.supers.time_createadd": 1523472105000, 
        "api.supers.time_createadd_to_dataset": 1523472108000, 
        "api.supers.time_installr": 1523472112000, 
        "api.supers.time_ls": 1523472120000, 
        "api.supers.time_ls_recursive": 1523472124000, 
        "api.supers.time_ls_recursive_long_all": 1523472128000, 
        "api.supers.time_remove": 1523472133000, 
        "api.testds.time_create_test_dataset1": 1523472137000, 
        "api.testds.time_create_test_dataset2x2": 1523472138000, 
        "core.runner.time_echo": 1523472144000, 
        "core.runner.time_echo_gitrunner": 1523472149000, 
        "core.startup.time_help_np": 1523472155000, 
        "core.startup.time_import": 1523472157000, 
        "core.startup.time_import_api": 1523472160000
    }, 
    "version": 1
}