{
    "benchmark_version": {
        "api.supers.time_createadd": "9627ffa29956a92e4610615ede7b621bbe831df9d5aaf99d228a681b49a65b1f", 
        "api.supers.time_createadd_to_dataset": "994ddd7edd278a30db53653e54e9976a39e1bde83b663d095e76217d683e1992", 
        "api.supers.time_installr": "f9cd0ceef63e4692e520a08a0d61942b9f08151fbe0ff38bc562aab505e7d204", 
        "api.supers.time_ls": "090ffbfc5ed895f49055534c197753baacb35f8bb3c1a69013c1011738ca300f", 
        "api.supers.time_ls_recursive": "d02744c6b0c50fb150b7e596ca541160f70a4933daac66d3b78b7ccdd6fc6c2f", 
        "api.supers.time_ls_recursive_long_all": "b87eb69e3352d67e40bc22b3f54e9be3b4f11eeb821186da240031e4953764b9", 
        "api.supers.time_remove": "d90e236129ab9910e61fb2ce6efa667543c915f46b937ef5187a0658369b4fa0", 
        "api.testds.time_create_test_dataset1": "9ecd497c5dd148ef03187ff8e66872e3a1ae97083bbf12e726b9fadfc6358f8e", 
        "api.testds.time_create_test_dataset2x2": "fca09bf52102f408d7d0a57e79ddbbb329eda25dffaf38c863f3271f7b7547c0", 
        "core.runner.time_echo": "fa3e886cf31276383138dcece3a41704add08700c4c756bcd65830edd5f87764", 
        "core.runner.time_echo_gitrunner": "e128fce0653554d3d8f58f8b55c32414bb826b3ca7350b43cbf171ce3e6f6e32", 
        "core.startup.time_help_np": "78c62df8b90b52ee22470b016afc051ef28ea2b4598ecaf3337d7c1d8a142479", 
        "core.startup.time_import": "5a62b417a0fe0b72410c5ac3b48be93ecac330c06565763b0209e5d0fedcc05e", 
        "core.startup.time_import_api": "ad7803b5cd3d3e2b45adbdbf8df9b4a3d483d0da621644a9476182740cb46246"
    }, 
    "commit_hash": "56fca930ac09fc3fffb8b341e07cb9ad783aeb2e", 
    "date": 1539692252000, 
    "ended_at": {
        "api.supers.time_createadd": 1541690545247, 
        "api.supers.time_createadd_to_dataset": 1541690545248, 
        "api.supers.time_installr": 1541690545248, 
        "api.supers.time_ls": 1541690545248, 
        "api.supers.time_ls_recursive": 1541690545249, 
        "api.supers.time_ls_recursive_long_all": 1541690545249, 
        "api.supers.time_remove": 1541690545250, 
        "api.testds.time_create_test_dataset1": 1541690557311, 
        "api.testds.time_create_test_dataset2x2": 1541690547760, 
        "core.runner.time_echo": 1541690557515, 
        "core.runner.time_echo_gitrunner": 1541690557720, 
        "core.startup.time_help_np": 1541690561182, 
        "core.startup.time_import": 1541690562188, 
        "core.startup.time_import_api": 1541690565298
    }, 
    "env_name": "virtualenv-py3.4", 
    "params": {
        "arch": "x86_64", 
        "cpu": "Intel(R) Xeon(R) CPU E5-1607 v2 @ 3.00GHz", 
        "machine": "drogon-neurodebian1.1", 
        "os": "Linux 4.6.0-rc1+", 
        "python": "3.4", 
        "ram": "65948008"
    }, 
    "profiles": {}, 
    "python": "3.4", 
    "requirements": {}, 
    "results": {
        "api.supers.time_createadd": null, 
        "api.supers.time_createadd_to_dataset": null, 
        "api.supers.time_installr": null, 
        "api.supers.time_ls": null, 
        "api.supers.time_ls_recursive": null, 
        "api.supers.time_ls_recursive_long_all": null, 
        "api.supers.time_remove": null, 
        "api.testds.time_create_test_dataset1": {
            "result": [
                0.26569610089063644
            ], 
            "stats": [
                {
                    "ci_99": [
                        0.2619437277317047, 
                        0.3072785288095474
                    ], 
                    "max": 0.3072785288095474, 
                    "mean": 0.27118897885084153, 
                    "min": 0.2619437277317047, 
                    "number": 1, 
                    "q_25": 0.26379750622436404, 
                    "q_75": 0.27309830812737346, 
                    "repeat": 10, 
                    "std": 0.01301098165895408
                }
            ]
        }, 
        "api.testds.time_create_test_dataset2x2": null, 
        "core.runner.time_echo": {
            "result": [
                0.0014923825593931334
            ], 
            "stats": [
                {
                    "ci_99": [
                        0.0014745164662599564, 
                        0.00153012786592756
                    ], 
                    "max": 0.00153012786592756, 
                    "mean": 0.0014949058315583638, 
                    "min": 0.0014745164662599564, 
                    "number": 7, 
                    "q_25": 0.0014843444472977094, 
                    "q_75": 0.001502996776252985, 
                    "repeat": 10, 
                    "std": 1.527447241579357e-05
                }
            ]
        }, 
        "core.runner.time_echo_gitrunner": {
            "result": [
                0.002562817884609103
            ], 
            "stats": [
                {
                    "ci_99": [
                        0.0023190267384052277, 
                        0.0028927670791745186
                    ], 
                    "max": 0.0028927670791745186, 
                    "mean": 0.0025648126378655435, 
                    "min": 0.0023190267384052277, 
                    "number": 4, 
                    "q_25": 0.0024271825095638633, 
                    "q_75": 0.002667170949280262, 
                    "repeat": 10, 
                    "std": 0.00016550068932757724
                }
            ]
        }, 
        "core.startup.time_help_np": {
            "result": [
                0.583720768801868
            ], 
            "stats": [
                {
                    "ci_99": [
                        0.5299268905073404, 
                        0.6008110791444778
                    ], 
                    "max": 0.6008110791444778, 
                    "mean": 0.5665185345336795, 
                    "min": 0.5299268905073404, 
                    "number": 1, 
                    "q_25": 0.5332770957611501, 
                    "q_75": 0.588482616469264, 
                    "repeat": 10, 
                    "std": 0.02797624053410608
                }
            ]
        }, 
        "core.startup.time_import": {
            "result": [
                0.15349913947284222
            ], 
            "stats": [
                {
                    "ci_99": [
                        0.10682257078588009, 
                        0.16420899517834187
                    ], 
                    "max": 0.16420899517834187, 
                    "mean": 0.13748876862227916, 
                    "min": 0.10682257078588009, 
                    "number": 1, 
                    "q_25": 0.10833303909748793, 
                    "q_75": 0.15649623330682516, 
                    "repeat": 10, 
                    "std": 0.024176742747051918
                }
            ]
        }, 
        "core.startup.time_import_api": {
            "result": [
                0.5149936275556684
            ], 
            "stats": [
                {
                    "ci_99": [
                        0.4637196268886328, 
                        0.5309944432228804
                    ], 
                    "max": 0.5309944432228804, 
                    "mean": 0.5099766841158271, 
                    "min": 0.4637196268886328, 
                    "number": 1, 
                    "q_25": 0.5050687999464571, 
                    "q_75": 0.5212000282481313, 
                    "repeat": 10, 
                    "std": 0.017905709977473584
                }
            ]
        }
    }, 
    "started_at": {
        "api.supers.time_createadd": 1541690544092, 
        "api.supers.time_createadd_to_dataset": 1541690545247, 
        "api.supers.time_installr": 1541690545248, 
        "api.supers.time_ls": 1541690545248, 
        "api.supers.time_ls_recursive": 1541690545249, 
        "api.supers.time_ls_recursive_long_all": 1541690545249, 
        "api.supers.time_remove": 1541690545249, 
        "api.testds.time_create_test_dataset1": 1541690555545, 
        "api.testds.time_create_test_dataset2x2": 1541690546957, 
        "core.runner.time_echo": 1541690557312, 
        "core.runner.time_echo_gitrunner": 1541690557516, 
        "core.startup.time_help_np": 1541690557721, 
        "core.startup.time_import": 1541690561183, 
        "core.startup.time_import_api": 1541690562189
    }, 
    "version": 1
}