{
    "commit_hash": "5dd6abc4cc01239bb4a7090b7a6c3045ab0ef595", 
    "date": 1513089843000, 
    "ended_at": {
        "api.supers.time_createadd": 1517845126000, 
        "api.supers.time_createadd_to_dataset": 1517845129000, 
        "api.supers.time_installr": 1517845138000, 
        "api.supers.time_ls": 1517845141000, 
        "api.supers.time_ls_recursive": 1519437930000, 
        "api.supers.time_ls_recursive_long_all": 1519437934000, 
        "api.supers.time_remove": 1517845147000, 
        "api.testds.time_create_test_dataset1": 1517845148000, 
        "api.testds.time_create_test_dataset2x2": 1517845153000, 
        "core.runner.time_echo": 1517845157000, 
        "core.runner.time_echo_gitrunner": 1517845162000, 
        "core.startup.time_help_np": 1517845163000, 
        "core.startup.time_import": 1517845166000, 
        "core.startup.time_import_api": 1517845167000
    }, 
    "env_name": "virtualenv-py2.7", 
    "params": {
        "arch": "x86_64", 
        "cpu": "Intel(R) Xeon(R) CPU E5-1607 v2 @ 3.00GHz", 
        "machine": "drogon-neurodebian1.1", 
        "os": "Linux 4.6.0-rc1+", 
        "python": "2.7", 
        "ram": "65948008"
    }, 
    "profiles": {}, 
    "python": "2.7", 
    "requirements": {}, 
    "results": {
        "api.supers.time_createadd": 0.8220632076263428, 
        "api.supers.time_createadd_to_dataset": 0.8098659515380859, 
        "api.supers.time_installr": 2.683218002319336, 
        "api.supers.time_ls": 0.08306951522827148, 
        "api.supers.time_ls_recursive": 1.0640051364898682, 
        "api.supers.time_ls_recursive_long_all": 1.2524230480194092, 
        "api.supers.time_remove": 1.7550690174102783, 
        "api.testds.time_create_test_dataset1": 0.2142181396484375, 
        "api.testds.time_create_test_dataset2x2": 1.5713839530944824, 
        "core.runner.time_echo": 0.0012490761280059815, 
        "core.runner.time_echo_gitrunner": 0.0014587688446044923, 
        "core.startup.time_help_np": 0.29525184631347656, 
        "core.startup.time_import": 0.07405309677124024, 
        "core.startup.time_import_api": 0.24330997467041016
    }, 
    "started_at": {
        "api.supers.time_createadd": 1517845123000, 
        "api.supers.time_createadd_to_dataset": 1517845126000, 
        "api.supers.time_installr": 1517845129000, 
        "api.supers.time_ls": 1517845138000, 
        "api.supers.time_ls_recursive": 1519437926000, 
        "api.supers.time_ls_recursive_long_all": 1519437930000, 
        "api.supers.time_remove": 1517845141000, 
        "api.testds.time_create_test_dataset1": 1517845147000, 
        "api.testds.time_create_test_dataset2x2": 1517845148000, 
        "core.runner.time_echo": 1517845153000, 
        "core.runner.time_echo_gitrunner": 1517845157000, 
        "core.startup.time_help_np": 1517845162000, 
        "core.startup.time_import": 1517845163000, 
        "core.startup.time_import_api": 1517845166000
    }, 
    "version": 1
}