{
    "commit_hash": "69bd1b20cd6c4eddfb591c13b43a2580945320b4", 
    "date": 1484821358000, 
    "ended_at": {
        "api.supers.time_createadd": 1504889185000, 
        "api.supers.time_createadd_to_dataset": 1504889190000, 
        "api.supers.time_installr": 1504889198000, 
        "api.supers.time_ls": 1504889203000, 
        "api.supers.time_ls_recursive": 1519431624000, 
        "api.supers.time_ls_recursive_long_all": 1519431625000, 
        "api.supers.time_remove": 1504889205000, 
        "api.testds.time_create_test_dataset1": 1504889207000, 
        "api.testds.time_create_test_dataset2x2": 1504889218000, 
        "core.runner.time_echo": 1504889222000, 
        "core.runner.time_echo_gitrunner": 1504889228000, 
        "core.startup.time_help_np": 1504889229000, 
        "core.startup.time_import": 1504889231000, 
        "core.startup.time_import_api": 1504889232000
    }, 
    "env_name": "virtualenv-py2.7", 
    "params": {
        "arch": "x86_64", 
        "cpu": "Intel(R) Xeon(R) CPU E5-1607 v2 @ 3.00GHz", 
        "machine": "drogon-neurodebian1.1", 
        "os": "Linux 4.6.0-rc1+", 
        "python": "2.7", 
        "ram": "65948008"
    }, 
    "profiles": {}, 
    "python": "2.7", 
    "requirements": {}, 
    "results": {
        "api.supers.time_createadd": 1.14469313621521, 
        "api.supers.time_createadd_to_dataset": 1.3549978733062744, 
        "api.supers.time_installr": 2.5425519943237305, 
        "api.supers.time_ls": 0.1253683090209961, 
        "api.supers.time_ls_recursive": 0.8912019729614258, 
        "api.supers.time_ls_recursive_long_all": null, 
        "api.supers.time_remove": null, 
        "api.testds.time_create_test_dataset1": 0.4442439079284668, 
        "api.testds.time_create_test_dataset2x2": 3.437263011932373, 
        "core.runner.time_echo": 0.001381540060043335, 
        "core.runner.time_echo_gitrunner": 0.0015936250686645508, 
        "core.startup.time_help_np": 0.42539095878601074, 
        "core.startup.time_import": 0.052962303161621094, 
        "core.startup.time_import_api": 0.15450692176818848
    }, 
    "started_at": {
        "api.supers.time_createadd": 1504889181000, 
        "api.supers.time_createadd_to_dataset": 1504889185000, 
        "api.supers.time_installr": 1504889190000, 
        "api.supers.time_ls": 1504889198000, 
        "api.supers.time_ls_recursive": 1519431621000, 
        "api.supers.time_ls_recursive_long_all": 1519431624000, 
        "api.supers.time_remove": 1504889203000, 
        "api.testds.time_create_test_dataset1": 1504889205000, 
        "api.testds.time_create_test_dataset2x2": 1504889207000, 
        "core.runner.time_echo": 1504889218000, 
        "core.runner.time_echo_gitrunner": 1504889222000, 
        "core.startup.time_help_np": 1504889228000, 
        "core.startup.time_import": 1504889229000, 
        "core.startup.time_import_api": 1504889231000
    }, 
    "version": 1
}