{
    "commit_hash": "6f3c716159b909ca05ba8eb30edcba772b55954f", 
    "date": 1486577895000, 
    "ended_at": {
        "benchmarks.CreateTestDatasetSuite.time_create_test_dataset1": 1496433233000, 
        "benchmarks.CreateTestDatasetSuite.time_create_test_dataset2x2": 1496433241000, 
        "benchmarks.RunnerSuite.time_echo": 1496433245000, 
        "benchmarks.RunnerSuite.time_echo_gitrunner": 1496433251000, 
        "benchmarks.StartupSuite.time_help_np": 1496433252000, 
        "benchmarks.StartupSuite.time_import": 1496433256000, 
        "benchmarks.StartupSuite.time_import_api": 1496433257000, 
        "benchmarks.SuperdatasetsOperationsSuite.time_createadd": 1496433266000, 
        "benchmarks.SuperdatasetsOperationsSuite.time_createadd_to_dataset": 1496433271000, 
        "benchmarks.SuperdatasetsOperationsSuite.time_installr": 1496433279000, 
        "benchmarks.SuperdatasetsOperationsSuite.time_ls": 1496433280000, 
        "benchmarks.SuperdatasetsOperationsSuite.time_remove": 1496433291000
    }, 
    "env_name": "virtualenv-py3.4", 
    "params": {
        "arch": "x86_64", 
        "cpu": "Intel(R) Xeon(R) CPU E5-1607 v2 @ 3.00GHz", 
        "machine": "drogon-neurodebian1.1", 
        "os": "Linux 4.6.0-rc1+", 
        "python": "3.4", 
        "ram": "65948008"
    }, 
    "profiles": {}, 
    "python": "3.4", 
    "requirements": {}, 
    "results": {
        "benchmarks.CreateTestDatasetSuite.time_create_test_dataset1": 0.26814262568950653, 
        "benchmarks.CreateTestDatasetSuite.time_create_test_dataset2x2": 2.413029633462429, 
        "benchmarks.RunnerSuite.time_echo": 0.0012701097503304481, 
        "benchmarks.RunnerSuite.time_echo_gitrunner": 0.001767059862613678, 
        "benchmarks.StartupSuite.time_help_np": 0.47067268192768097, 
        "benchmarks.StartupSuite.time_import": 0.09985402189195156, 
        "benchmarks.StartupSuite.time_import_api": 0.22558127716183662, 
        "benchmarks.SuperdatasetsOperationsSuite.time_createadd": 1.1111396104097366, 
        "benchmarks.SuperdatasetsOperationsSuite.time_createadd_to_dataset": 1.2549020051956177, 
        "benchmarks.SuperdatasetsOperationsSuite.time_installr": 2.66781472787261, 
        "benchmarks.SuperdatasetsOperationsSuite.time_ls": null, 
        "benchmarks.SuperdatasetsOperationsSuite.time_remove": 3.4758654832839966
    }, 
    "started_at": {
        "benchmarks.CreateTestDatasetSuite.time_create_test_dataset1": 1496433232000, 
        "benchmarks.CreateTestDatasetSuite.time_create_test_dataset2x2": 1496433233000, 
        "benchmarks.RunnerSuite.time_echo": 1496433241000, 
        "benchmarks.RunnerSuite.time_echo_gitrunner": 1496433245000, 
        "benchmarks.StartupSuite.time_help_np": 1496433251000, 
        "benchmarks.StartupSuite.time_import": 1496433252000, 
        "benchmarks.StartupSuite.time_import_api": 1496433256000, 
        "benchmarks.SuperdatasetsOperationsSuite.time_createadd": 1496433262000, 
        "benchmarks.SuperdatasetsOperationsSuite.time_createadd_to_dataset": 1496433266000, 
        "benchmarks.SuperdatasetsOperationsSuite.time_installr": 1496433271000, 
        "benchmarks.SuperdatasetsOperationsSuite.time_ls": 1496433279000, 
        "benchmarks.SuperdatasetsOperationsSuite.time_remove": 1496433280000
    }, 
    "version": 1
}