{
    "benchmark_version": {
        "api.supers.time_createadd": "9627ffa29956a92e4610615ede7b621bbe831df9d5aaf99d228a681b49a65b1f", 
        "api.supers.time_createadd_to_dataset": "994ddd7edd278a30db53653e54e9976a39e1bde83b663d095e76217d683e1992", 
        "api.supers.time_installr": "f9cd0ceef63e4692e520a08a0d61942b9f08151fbe0ff38bc562aab505e7d204", 
        "api.supers.time_ls": "090ffbfc5ed895f49055534c197753baacb35f8bb3c1a69013c1011738ca300f", 
        "api.supers.time_ls_recursive": "d02744c6b0c50fb150b7e596ca541160f70a4933daac66d3b78b7ccdd6fc6c2f", 
        "api.supers.time_ls_recursive_long_all": "b87eb69e3352d67e40bc22b3f54e9be3b4f11eeb821186da240031e4953764b9", 
        "api.supers.time_remove": "d90e236129ab9910e61fb2ce6efa667543c915f46b937ef5187a0658369b4fa0", 
        "api.testds.time_create_test_dataset1": "9ecd497c5dd148ef03187ff8e66872e3a1ae97083bbf12e726b9fadfc6358f8e", 
        "api.testds.time_create_test_dataset2x2": "fca09bf52102f408d7d0a57e79ddbbb329eda25dffaf38c863f3271f7b7547c0", 
        "core.runner.time_echo": "fa3e886cf31276383138dcece3a41704add08700c4c756bcd65830edd5f87764", 
        "core.runner.time_echo_gitrunner": "e128fce0653554d3d8f58f8b55c32414bb826b3ca7350b43cbf171ce3e6f6e32", 
        "core.startup.time_help_np": "78c62df8b90b52ee22470b016afc051ef28ea2b4598ecaf3337d7c1d8a142479", 
        "core.startup.time_import": "5a62b417a0fe0b72410c5ac3b48be93ecac330c06565763b0209e5d0fedcc05e", 
        "core.startup.time_import_api": "ad7803b5cd3d3e2b45adbdbf8df9b4a3d483d0da621644a9476182740cb46246"
    }, 
    "commit_hash": "820c8cc9de63c8732bbf37a5bfea7a96adfb62e5", 
    "date": 1537567707000, 
    "ended_at": {
        "api.supers.time_createadd": 1541477830334, 
        "api.supers.time_createadd_to_dataset": 1541477830334, 
        "api.supers.time_installr": 1541477830334, 
        "api.supers.time_ls": 1541477830335, 
        "api.supers.time_ls_recursive": 1541477830335, 
        "api.supers.time_ls_recursive_long_all": 1541477830335, 
        "api.supers.time_remove": 1541477830335, 
        "api.testds.time_create_test_dataset1": 1541477840682, 
        "api.testds.time_create_test_dataset2x2": 1541477832294, 
        "core.runner.time_echo": 1541477840885, 
        "core.runner.time_echo_gitrunner": 1541477841090, 
        "core.startup.time_help_np": 1541477844152, 
        "core.startup.time_import": 1541477844709, 
        "core.startup.time_import_api": 1541477847318
    }, 
    "env_name": "virtualenv-py2.7", 
    "params": {
        "arch": "x86_64", 
        "cpu": "Intel(R) Xeon(R) CPU E5-1607 v2 @ 3.00GHz", 
        "machine": "drogon-neurodebian1.1", 
        "os": "Linux 4.6.0-rc1+", 
        "python": "2.7", 
        "ram": "65948008"
    }, 
    "profiles": {}, 
    "python": "2.7", 
    "requirements": {}, 
    "results": {
        "api.supers.time_createadd": null, 
        "api.supers.time_createadd_to_dataset": null, 
        "api.supers.time_installr": null, 
        "api.supers.time_ls": null, 
        "api.supers.time_ls_recursive": null, 
        "api.supers.time_ls_recursive_long_all": null, 
        "api.supers.time_remove": null, 
        "api.testds.time_create_test_dataset1": {
            "result": [
                0.2799419164657593
            ], 
            "stats": [
                {
                    "ci_99": [
                        0.2764410972595215, 
                        0.28280091285705566
                    ], 
                    "max": 0.28280091285705566, 
                    "mean": 0.2794121503829956, 
                    "min": 0.2764410972595215, 
                    "number": 1, 
                    "q_25": 0.27839040756225586, 
                    "q_75": 0.2803049087524414, 
                    "repeat": 10, 
                    "std": 0.0017857134170199546
                }
            ]
        }, 
        "api.testds.time_create_test_dataset2x2": null, 
        "core.runner.time_echo": {
            "result": [
                0.001724566732134138
            ], 
            "stats": [
                {
                    "ci_99": [
                        0.0016208716801234654, 
                        0.0019878659929547992
                    ], 
                    "max": 0.0019878659929547992, 
                    "mean": 0.0017517021724155972, 
                    "min": 0.0016208716801234654, 
                    "number": 7, 
                    "q_25": 0.0016536797795976912, 
                    "q_75": 0.0018031086240495955, 
                    "repeat": 10, 
                    "std": 0.00011562585036027744
                }
            ]
        }, 
        "core.runner.time_echo_gitrunner": {
            "result": [
                0.0027529895305633545
            ], 
            "stats": [
                {
                    "ci_99": [
                        0.0023744702339172363, 
                        0.002954721450805664
                    ], 
                    "max": 0.002954721450805664, 
                    "mean": 0.0026912450790405273, 
                    "min": 0.0023744702339172363, 
                    "number": 4, 
                    "q_25": 0.0024872571229934692, 
                    "q_75": 0.002850666642189026, 
                    "repeat": 10, 
                    "std": 0.00019919578931327484
                }
            ]
        }, 
        "core.startup.time_help_np": {
            "result": [
                0.5012924671173096
            ], 
            "stats": [
                {
                    "ci_99": [
                        0.44858288764953613, 
                        0.5125570297241211
                    ], 
                    "max": 0.5125570297241211, 
                    "mean": 0.4959025621414185, 
                    "min": 0.44858288764953613, 
                    "number": 1, 
                    "q_25": 0.4958016872406006, 
                    "q_75": 0.5058197975158691, 
                    "repeat": 10, 
                    "std": 0.01766737508678091
                }
            ]
        }, 
        "core.startup.time_import": {
            "result": [
                0.07650601863861084
            ], 
            "stats": [
                {
                    "ci_99": [
                        0.0756220817565918, 
                        0.10078191757202148
                    ], 
                    "max": 0.10078191757202148, 
                    "mean": 0.08114550113677979, 
                    "min": 0.0756220817565918, 
                    "number": 1, 
                    "q_25": 0.07608747482299805, 
                    "q_75": 0.08234381675720215, 
                    "repeat": 10, 
                    "std": 0.008392920962208833
                }
            ]
        }, 
        "core.startup.time_import_api": {
            "result": [
                0.43771934509277344
            ], 
            "stats": [
                {
                    "ci_99": [
                        0.3816721439361572, 
                        0.4536609649658203
                    ], 
                    "max": 0.4536609649658203, 
                    "mean": 0.4293501615524292, 
                    "min": 0.3816721439361572, 
                    "number": 1, 
                    "q_25": 0.4250847101211548, 
                    "q_75": 0.448708176612854, 
                    "repeat": 10, 
                    "std": 0.02443514493167165
                }
            ]
        }
    }, 
    "started_at": {
        "api.supers.time_createadd": 1541477829677, 
        "api.supers.time_createadd_to_dataset": 1541477830334, 
        "api.supers.time_installr": 1541477830334, 
        "api.supers.time_ls": 1541477830334, 
        "api.supers.time_ls_recursive": 1541477830335, 
        "api.supers.time_ls_recursive_long_all": 1541477830335, 
        "api.supers.time_remove": 1541477830335, 
        "api.testds.time_create_test_dataset1": 1541477838927, 
        "api.testds.time_create_test_dataset2x2": 1541477832092, 
        "core.runner.time_echo": 1541477840683, 
        "core.runner.time_echo_gitrunner": 1541477840886, 
        "core.startup.time_help_np": 1541477841091, 
        "core.startup.time_import": 1541477844152, 
        "core.startup.time_import_api": 1541477844710
    }, 
    "version": 1
}