{
    "commit_hash": "8e6684aa798f37a391ca45ef651956f4ecdf862b", 
    "date": 1497259090000, 
    "ended_at": {
        "api.supers.time_createadd": 1499373576000, 
        "api.supers.time_createadd_to_dataset": 1499373579000, 
        "api.supers.time_installr": 1499373590000, 
        "api.supers.time_ls": 1499373595000, 
        "api.supers.time_remove": 1499373595000, 
        "api.testds.time_create_test_dataset1": 1499373597000, 
        "api.testds.time_create_test_dataset2x2": 1499373603000, 
        "core.runner.time_echo": 1499373607000, 
        "core.runner.time_echo_gitrunner": 1499373613000, 
        "core.startup.time_help_np": 1499373614000, 
        "core.startup.time_import": 1499373617000, 
        "core.startup.time_import_api": 1499373618000
    }, 
    "env_name": "virtualenv-py2.7", 
    "params": {
        "arch": "x86_64", 
        "cpu": "Intel(R) Xeon(R) CPU E5-1607 v2 @ 3.00GHz", 
        "machine": "drogon-neurodebian1.1", 
        "os": "Linux 4.6.0-rc1+", 
        "python": "2.7", 
        "ram": "65948008"
    }, 
    "profiles": {}, 
    "python": "2.7", 
    "requirements": {}, 
    "results": {
        "api.supers.time_createadd": 0.8767421245574951, 
        "api.supers.time_createadd_to_dataset": 0.8325510025024414, 
        "api.supers.time_installr": 3.2672059535980225, 
        "api.supers.time_ls": 0.12751610279083253, 
        "api.supers.time_remove": null, 
        "api.testds.time_create_test_dataset1": 0.29291415214538574, 
        "api.testds.time_create_test_dataset2x2": 1.9859619140625, 
        "core.runner.time_echo": 0.001389752149581909, 
        "core.runner.time_echo_gitrunner": 0.0016108491420745849, 
        "core.startup.time_help_np": 0.2565798759460449, 
        "core.startup.time_import": 0.08852510452270508, 
        "core.startup.time_import_api": 0.20591306686401367
    }, 
    "started_at": {
        "api.supers.time_createadd": 1499373573000, 
        "api.supers.time_createadd_to_dataset": 1499373576000, 
        "api.supers.time_installr": 1499373579000, 
        "api.supers.time_ls": 1499373590000, 
        "api.supers.time_remove": 1499373595000, 
        "api.testds.time_create_test_dataset1": 1499373595000, 
        "api.testds.time_create_test_dataset2x2": 1499373597000, 
        "core.runner.time_echo": 1499373603000, 
        "core.runner.time_echo_gitrunner": 1499373607000, 
        "core.startup.time_help_np": 1499373613000, 
        "core.startup.time_import": 1499373614000, 
        "core.startup.time_import_api": 1499373617000
    }, 
    "version": 1
}