{
    "commit_hash": "a1b2fd1b0aa61fdec1693d2ed16fbd87879d614b", 
    "date": 1487167013000, 
    "ended_at": {
        "api.supers.time_createadd": 1499371016000, 
        "api.supers.time_createadd_to_dataset": 1499371020000, 
        "api.supers.time_installr": 1499371028000, 
        "api.supers.time_ls": 1499371032000, 
        "api.supers.time_remove": 1499371042000, 
        "api.testds.time_create_test_dataset1": 1499371043000, 
        "api.testds.time_create_test_dataset2x2": 1499371050000, 
        "core.runner.time_echo": 1499371054000, 
        "core.runner.time_echo_gitrunner": 1499371059000, 
        "core.startup.time_help_np": 1499371060000, 
        "core.startup.time_import": 1499371063000, 
        "core.startup.time_import_api": 1499371068000
    }, 
    "env_name": "virtualenv-py2.7", 
    "params": {
        "arch": "x86_64", 
        "cpu": "Intel(R) Xeon(R) CPU E5-1607 v2 @ 3.00GHz", 
        "machine": "drogon-neurodebian1.1", 
        "os": "Linux 4.6.0-rc1+", 
        "python": "2.7", 
        "ram": "65948008"
    }, 
    "profiles": {}, 
    "python": "2.7", 
    "requirements": {}, 
    "results": {
        "api.supers.time_createadd": 1.022303819656372, 
        "api.supers.time_createadd_to_dataset": 1.1839921474456787, 
        "api.supers.time_installr": 2.4923009872436523, 
        "api.supers.time_ls": 0.08789379596710205, 
        "api.supers.time_remove": 3.028409957885742, 
        "api.testds.time_create_test_dataset1": 0.26461005210876465, 
        "api.testds.time_create_test_dataset2x2": 2.1670258045196533, 
        "core.runner.time_echo": 0.001313601016998291, 
        "core.runner.time_echo_gitrunner": 0.0015436809062957765, 
        "core.startup.time_help_np": 0.4257969856262207, 
        "core.startup.time_import": 0.05969269275665283, 
        "core.startup.time_import_api": 0.16220469474792482
    }, 
    "started_at": {
        "api.supers.time_createadd": 1499371013000, 
        "api.supers.time_createadd_to_dataset": 1499371016000, 
        "api.supers.time_installr": 1499371020000, 
        "api.supers.time_ls": 1499371028000, 
        "api.supers.time_remove": 1499371032000, 
        "api.testds.time_create_test_dataset1": 1499371042000, 
        "api.testds.time_create_test_dataset2x2": 1499371043000, 
        "core.runner.time_echo": 1499371050000, 
        "core.runner.time_echo_gitrunner": 1499371054000, 
        "core.startup.time_help_np": 1499371059000, 
        "core.startup.time_import": 1499371060000, 
        "core.startup.time_import_api": 1499371063000
    }, 
    "version": 1
}