{
    "commit_hash": "b2b1628b3f8240ef2b73318f783f5aef2ac5b817", 
    "date": 1512738790000, 
    "ended_at": {
        "api.supers.time_createadd": 1517843345000, 
        "api.supers.time_createadd_to_dataset": 1517843348000, 
        "api.supers.time_installr": 1517843356000, 
        "api.supers.time_ls": 1517843360000, 
        "api.supers.time_ls_recursive": 1519420806000, 
        "api.supers.time_ls_recursive_long_all": 1519420811000, 
        "api.supers.time_remove": 1517843367000, 
        "api.testds.time_create_test_dataset1": 1517843368000, 
        "api.testds.time_create_test_dataset2x2": 1517843374000, 
        "core.runner.time_echo": 1517843378000, 
        "core.runner.time_echo_gitrunner": 1517843383000, 
        "core.startup.time_help_np": 1517843385000, 
        "core.startup.time_import": 1517843389000, 
        "core.startup.time_import_api": 1517843390000
    }, 
    "env_name": "virtualenv-py3.4", 
    "params": {
        "arch": "x86_64", 
        "cpu": "Intel(R) Xeon(R) CPU E5-1607 v2 @ 3.00GHz", 
        "machine": "drogon-neurodebian1.1", 
        "os": "Linux 4.6.0-rc1+", 
        "python": "3.4", 
        "ram": "65948008"
    }, 
    "profiles": {}, 
    "python": "3.4", 
    "requirements": {}, 
    "results": {
        "api.supers.time_createadd": 0.8117087999999058, 
        "api.supers.time_createadd_to_dataset": 0.8204842740001368, 
        "api.supers.time_installr": 2.5437686000000213, 
        "api.supers.time_ls": 0.09692570719998912, 
        "api.supers.time_ls_recursive": 1.0795398198533803, 
        "api.supers.time_ls_recursive_long_all": 1.213118399027735, 
        "api.supers.time_remove": 1.8474425539998265, 
        "api.testds.time_create_test_dataset1": 0.21189565600025162, 
        "api.testds.time_create_test_dataset2x2": 1.8811822829998164, 
        "core.runner.time_echo": 0.0011318592140000874, 
        "core.runner.time_echo_gitrunner": 0.0015712335559996972, 
        "core.startup.time_help_np": 0.4247494689998348, 
        "core.startup.time_import": 0.11138815229996908, 
        "core.startup.time_import_api": 0.33292948400003297
    }, 
    "started_at": {
        "api.supers.time_createadd": 1517843341000, 
        "api.supers.time_createadd_to_dataset": 1517843345000, 
        "api.supers.time_installr": 1517843348000, 
        "api.supers.time_ls": 1517843356000, 
        "api.supers.time_ls_recursive": 1519420802000, 
        "api.supers.time_ls_recursive_long_all": 1519420806000, 
        "api.supers.time_remove": 1517843360000, 
        "api.testds.time_create_test_dataset1": 1517843367000, 
        "api.testds.time_create_test_dataset2x2": 1517843368000, 
        "core.runner.time_echo": 1517843374000, 
        "core.runner.time_echo_gitrunner": 1517843378000, 
        "core.startup.time_help_np": 1517843383000, 
        "core.startup.time_import": 1517843385000, 
        "core.startup.time_import_api": 1517843389000
    }, 
    "version": 1
}