{
    "commit_hash": "b8183663c974fa1293f03c134564fcb7e7e5e36f", 
    "date": 1512770306000, 
    "ended_at": {
        "api.supers.time_createadd": 1517845278000, 
        "api.supers.time_createadd_to_dataset": 1517845281000, 
        "api.supers.time_installr": 1517845290000, 
        "api.supers.time_ls": 1517845293000, 
        "api.supers.time_ls_recursive": 1519437972000, 
        "api.supers.time_ls_recursive_long_all": 1519437976000, 
        "api.supers.time_remove": 1517845299000, 
        "api.testds.time_create_test_dataset1": 1517845300000, 
        "api.testds.time_create_test_dataset2x2": 1517845306000, 
        "core.runner.time_echo": 1517845310000, 
        "core.runner.time_echo_gitrunner": 1517845316000, 
        "core.startup.time_help_np": 1517845317000, 
        "core.startup.time_import": 1517845321000, 
        "core.startup.time_import_api": 1517845322000
    }, 
    "env_name": "virtualenv-py3.4", 
    "params": {
        "arch": "x86_64", 
        "cpu": "Intel(R) Xeon(R) CPU E5-1607 v2 @ 3.00GHz", 
        "machine": "drogon-neurodebian1.1", 
        "os": "Linux 4.6.0-rc1+", 
        "python": "3.4", 
        "ram": "65948008"
    }, 
    "profiles": {}, 
    "python": "3.4", 
    "requirements": {}, 
    "results": {
        "api.supers.time_createadd": 0.8098868549996041, 
        "api.supers.time_createadd_to_dataset": 0.8162957340000503, 
        "api.supers.time_installr": 2.5493232459994033, 
        "api.supers.time_ls": 0.08062087960006466, 
        "api.supers.time_ls_recursive": 1.0927190568763763, 
        "api.supers.time_ls_recursive_long_all": 1.202467975905165, 
        "api.supers.time_remove": 1.8519173810000211, 
        "api.testds.time_create_test_dataset1": 0.2119819939998706, 
        "api.testds.time_create_test_dataset2x2": 1.880985795000015, 
        "core.runner.time_echo": 0.0011245429649998186, 
        "core.runner.time_echo_gitrunner": 0.001577292793000197, 
        "core.startup.time_help_np": 0.3678271329999916, 
        "core.startup.time_import": 0.11359887169992362, 
        "core.startup.time_import_api": 0.30535921699993196
    }, 
    "started_at": {
        "api.supers.time_createadd": 1517845275000, 
        "api.supers.time_createadd_to_dataset": 1517845278000, 
        "api.supers.time_installr": 1517845281000, 
        "api.supers.time_ls": 1517845290000, 
        "api.supers.time_ls_recursive": 1519437968000, 
        "api.supers.time_ls_recursive_long_all": 1519437972000, 
        "api.supers.time_remove": 1517845293000, 
        "api.testds.time_create_test_dataset1": 1517845299000, 
        "api.testds.time_create_test_dataset2x2": 1517845300000, 
        "core.runner.time_echo": 1517845306000, 
        "core.runner.time_echo_gitrunner": 1517845310000, 
        "core.startup.time_help_np": 1517845316000, 
        "core.startup.time_import": 1517845317000, 
        "core.startup.time_import_api": 1517845321000
    }, 
    "version": 1
}