{
    "commit_hash": "007ada6cb918fdf412028caa5dbc7cd9f1dd65be", 
    "date": 1479832200000, 
    "ended_at": {
        "benchmarks.RunnerSuite.time_echo": 1484713589000, 
        "benchmarks.RunnerSuite.time_echo_gitrunner": 1484713591000, 
        "benchmarks.StartupSuite.time_help_np": 1484713593000, 
        "benchmarks.StartupSuite.time_import": 1484713595000, 
        "benchmarks.StartupSuite.time_import_api": 1484713596000
    }, 
    "env_name": "virtualenv-py2.7", 
    "params": {
        "arch": "x86_64", 
        "cpu": "Intel(R) Xeon(R) CPU E5-2623 v3 @ 3.00GHz", 
        "machine": "yoh@smaug", 
        "os": "Linux 4.9.0-rc2+", 
        "python": "2.7", 
        "ram": "128GB"
    }, 
    "profiles": {}, 
    "python": "2.7", 
    "requirements": {}, 
    "results": {
        "benchmarks.RunnerSuite.time_echo": 0.0033686494827270506, 
        "benchmarks.RunnerSuite.time_echo_gitrunner": 0.002667651176452637, 
        "benchmarks.StartupSuite.time_help_np": 0.40462589263916016, 
        "benchmarks.StartupSuite.time_import": 0.07894370555877686, 
        "benchmarks.StartupSuite.time_import_api": 0.22061610221862793
    }, 
    "started_at": {
        "benchmarks.RunnerSuite.time_echo": 1484713588000, 
        "benchmarks.RunnerSuite.time_echo_gitrunner": 1484713589000, 
        "benchmarks.StartupSuite.time_help_np": 1484713591000, 
        "benchmarks.StartupSuite.time_import": 1484713593000, 
        "benchmarks.StartupSuite.time_import_api": 1484713595000
    }, 
    "version": 1
}