{
    "commit_hash": "3226f6e510ae86a85f705e50cead081af9c6b797", 
    "date": 1465609128000, 
    "ended_at": {
        "benchmarks.RunnerSuite.time_echo": 1484632405000, 
        "benchmarks.RunnerSuite.time_echo_gitrunner": 1484632406000, 
        "benchmarks.StartupSuite.time_help_np": 1484632408000, 
        "benchmarks.StartupSuite.time_import": 1484632410000, 
        "benchmarks.StartupSuite.time_import_api": 1484632411000
    }, 
    "env_name": "virtualenv-py2.7", 
    "params": {
        "arch": "x86_64", 
        "cpu": "Intel(R) Xeon(R) CPU E5-2623 v3 @ 3.00GHz", 
        "machine": "yoh@smaug", 
        "os": "Linux 4.9.0-rc2+", 
        "python": "2.7", 
        "ram": "128GB"
    }, 
    "profiles": {}, 
    "python": "2.7", 
    "requirements": {}, 
    "results": {
        "benchmarks.RunnerSuite.time_echo": 0.0034897899627685546, 
        "benchmarks.RunnerSuite.time_echo_gitrunner": 0.003946869373321533, 
        "benchmarks.StartupSuite.time_help_np": 0.40869593620300293, 
        "benchmarks.StartupSuite.time_import": 0.0661912202835083, 
        "benchmarks.StartupSuite.time_import_api": 0.3140838146209717
    }, 
    "started_at": {
        "benchmarks.RunnerSuite.time_echo": 1484632404000, 
        "benchmarks.RunnerSuite.time_echo_gitrunner": 1484632405000, 
        "benchmarks.StartupSuite.time_help_np": 1484632406000, 
        "benchmarks.StartupSuite.time_import": 1484632408000, 
        "benchmarks.StartupSuite.time_import_api": 1484632410000
    }, 
    "version": 1
}