{
    "commit_hash": "9712b2e178f1db2df5779b5114ec340de38c7be7", 
    "date": 1465942700000, 
    "ended_at": {
        "benchmarks.RunnerSuite.time_echo": 1484632199000, 
        "benchmarks.RunnerSuite.time_echo_gitrunner": 1484632200000, 
        "benchmarks.StartupSuite.time_help_np": 1484632202000, 
        "benchmarks.StartupSuite.time_import": 1484632203000, 
        "benchmarks.StartupSuite.time_import_api": 1484632204000
    }, 
    "env_name": "virtualenv-py3.4", 
    "params": {
        "arch": "x86_64", 
        "cpu": "Intel(R) Xeon(R) CPU E5-2623 v3 @ 3.00GHz", 
        "machine": "yoh@smaug", 
        "os": "Linux 4.9.0-rc2+", 
        "python": "3.4", 
        "ram": "128GB"
    }, 
    "profiles": {}, 
    "python": "3.4", 
    "requirements": {}, 
    "results": {
        "benchmarks.RunnerSuite.time_echo": 0.003158752899616957, 
        "benchmarks.RunnerSuite.time_echo_gitrunner": 0.004055971195921302, 
        "benchmarks.StartupSuite.time_help_np": 0.5022829221561551, 
        "benchmarks.StartupSuite.time_import": 0.20681704860180616, 
        "benchmarks.StartupSuite.time_import_api": 0.39772631600499153
    }, 
    "started_at": {
        "benchmarks.RunnerSuite.time_echo": 1484632197000, 
        "benchmarks.RunnerSuite.time_echo_gitrunner": 1484632199000, 
        "benchmarks.StartupSuite.time_help_np": 1484632200000, 
        "benchmarks.StartupSuite.time_import": 1484632202000, 
        "benchmarks.StartupSuite.time_import_api": 1484632203000
    }, 
    "version": 1
}