{
    "commit_hash": "9e72df2f6aa23b0f3645a6419451cf589031769b", 
    "date": 1443647678000, 
    "ended_at": {
        "benchmarks.RunnerSuite.time_echo": 1484634307000, 
        "benchmarks.RunnerSuite.time_echo_gitrunner": 1484634307000, 
        "benchmarks.StartupSuite.time_help_np": 1484634309000, 
        "benchmarks.StartupSuite.time_import": 1484634312000, 
        "benchmarks.StartupSuite.time_import_api": 1484634313000
    }, 
    "env_name": "virtualenv-py3.4", 
    "params": {
        "arch": "x86_64", 
        "cpu": "Intel(R) Xeon(R) CPU E5-2623 v3 @ 3.00GHz", 
        "machine": "yoh@smaug", 
        "os": "Linux 4.9.0-rc2+", 
        "python": "3.4", 
        "ram": "128GB"
    }, 
    "profiles": {}, 
    "python": "3.4", 
    "requirements": {}, 
    "results": {
        "benchmarks.RunnerSuite.time_echo": 0.0029915880877524614, 
        "benchmarks.RunnerSuite.time_echo_gitrunner": null, 
        "benchmarks.StartupSuite.time_help_np": 0.3407420851290226, 
        "benchmarks.StartupSuite.time_import": 0.09868784742429852, 
        "benchmarks.StartupSuite.time_import_api": 0.35433195903897285
    }, 
    "started_at": {
        "benchmarks.RunnerSuite.time_echo": 1484634306000, 
        "benchmarks.RunnerSuite.time_echo_gitrunner": 1484634307000, 
        "benchmarks.StartupSuite.time_help_np": 1484634307000, 
        "benchmarks.StartupSuite.time_import": 1484634309000, 
        "benchmarks.StartupSuite.time_import_api": 1484634312000
    }, 
    "version": 1
}