{
    "commit_hash": "eb7f664b2d6ea05168dc65abfe133b7e38bd06c0", 
    "date": 1442826410000, 
    "ended_at": {
        "benchmarks.RunnerSuite.time_echo": 1484706211000, 
        "benchmarks.RunnerSuite.time_echo_gitrunner": 1484706211000, 
        "benchmarks.StartupSuite.time_help_np": 1484706212000, 
        "benchmarks.StartupSuite.time_import": 1484706214000, 
        "benchmarks.StartupSuite.time_import_api": 1484706215000
    }, 
    "env_name": "virtualenv-py2.7", 
    "params": {
        "arch": "x86_64", 
        "cpu": "Intel(R) Xeon(R) CPU E5-2623 v3 @ 3.00GHz", 
        "machine": "yoh@smaug", 
        "os": "Linux 4.9.0-rc2+", 
        "python": "2.7", 
        "ram": "128GB"
    }, 
    "profiles": {}, 
    "python": "2.7", 
    "requirements": {}, 
    "results": {
        "benchmarks.RunnerSuite.time_echo": 0.0033129310607910157, 
        "benchmarks.RunnerSuite.time_echo_gitrunner": null, 
        "benchmarks.StartupSuite.time_help_np": 0.32869791984558105, 
        "benchmarks.StartupSuite.time_import": 0.05637781620025635, 
        "benchmarks.StartupSuite.time_import_api": 0.28673410415649414
    }, 
    "started_at": {
        "benchmarks.RunnerSuite.time_echo": 1484706210000, 
        "benchmarks.RunnerSuite.time_echo_gitrunner": 1484706211000, 
        "benchmarks.StartupSuite.time_help_np": 1484706211000, 
        "benchmarks.StartupSuite.time_import": 1484706212000, 
        "benchmarks.StartupSuite.time_import_api": 1484706214000
    }, 
    "version": 1
}